tft/artemis_cli/__init__.py
tft/artemis_cli/artemis_cli.py
tft/artemis_cli/schemas/config.yaml
tft_artemis_cli-0.0.3.dist-info/LICENSE
tft_artemis_cli-0.0.3.dist-info/METADATA
tft_artemis_cli-0.0.3.dist-info/WHEEL
tft_artemis_cli-0.0.3.dist-info/entry_points.txt
tft_artemis_cli-0.0.3.dist-info/RECORD
