Metadata-Version: 2.1
Name: tft-artemis-cli
Version: 0.0.3
Summary: Command-line tool for Artemis service
License: Apache-2.0
Author: Milos Prchlik
Author-email: mprchlik@redhat.com
Requires-Python: >=3.9.0,<3.10.0
Classifier: License :: OSI Approved :: Apache Software License
Classifier: Programming Language :: Python :: 3
Classifier: Programming Language :: Python :: 3.9
Provides-Extra: full
Requires-Dist: click
Requires-Dist: click_completion
Requires-Dist: jq
Requires-Dist: jsonschema
Requires-Dist: prometheus-client
Requires-Dist: py-getch
Requires-Dist: pydantic
Requires-Dist: requests
Requires-Dist: rich
Requires-Dist: ruamel.yaml
Requires-Dist: semver
Requires-Dist: setuptools
Requires-Dist: stackprinter
Requires-Dist: urlnormalizer
